README.md
setup.py
cursy/__init__.py
cursy.egg-info/PKG-INFO
cursy.egg-info/SOURCES.txt
cursy.egg-info/dependency_links.txt
cursy.egg-info/top_level.txt